<?xml version="1.0"?>
<checkstyle><file name="modules/contrib/ckeditor_indentblock/ckeditor_indentblock.install"><error line="18" message="Call to deprecated function libraries_get_path():&#10;Will be removed before a stable Drupal 8 release. Please use the&#10;new library load and managment concepts described at:&#10;https://www.drupal.org/node/2170763" severity="error"/></file><file name="modules/contrib/ckeditor_indentblock/src/Plugin/CKEditorPlugin/IndentBlock.php"><error line="50" message="Call to deprecated function libraries_get_path():&#10;Will be removed before a stable Drupal 8 release. Please use the&#10;new library load and managment concepts described at:&#10;https://www.drupal.org/node/2170763" severity="error"/></file><file name="modules/contrib/ckeditor_indentblock/ckeditor_indentblock.info.yml"><error line="0" message="Add &lt;code&gt;core_version_requirement: ^8 || ^9&lt;/code&gt; to ckeditor_indentblock.info.yml to designate that the module is compatible with Drupal 9. See https://www.drupal.org/node/3070687." severity="error"/></file><file name="modules/contrib/ckeditor_indentblock/composer.json"><error line="0" message="The drupal/core requirement is not Drupal 9 compatible. Having a composer.json is not a requirement for Drupal 9 compatibility but if there is one, it should include a drupal/core requirement compatible with Drupal 9." severity="error"/></file></checkstyle>

