<?xml version="1.0"?>
<checkstyle><file name="modules/contrib/clickandpledge_connect/src/Controller/CnPController.php"><error line="206" message="Call to deprecated function drupal_get_user_timezone(). Deprecated in drupal:8.8.0 and is removed from drupal:9.0.0. Use&#10;date_default_timezone_get() instead." severity="warning"/><error line="545" message="Call to deprecated function drupal_get_user_timezone(). Deprecated in drupal:8.8.0 and is removed from drupal:9.0.0. Use&#10;date_default_timezone_get() instead." severity="warning"/></file><file name="modules/contrib/clickandpledge_connect/src/Form/AddChannelGroup.php"><error line="68" message="Call to deprecated function drupal_get_user_timezone(). Deprecated in drupal:8.8.0 and is removed from drupal:9.0.0. Use&#10;date_default_timezone_get() instead." severity="warning"/><error line="144" message="Call to deprecated function drupal_get_user_timezone(). Deprecated in drupal:8.8.0 and is removed from drupal:9.0.0. Use&#10;date_default_timezone_get() instead." severity="warning"/></file><file name="modules/contrib/clickandpledge_connect/src/Form/AddFormGroup.php"><error line="68" message="Call to deprecated function drupal_get_user_timezone(). Deprecated in drupal:8.8.0 and is removed from drupal:9.0.0. Use&#10;date_default_timezone_get() instead." severity="warning"/><error line="183" message="Call to deprecated function drupal_get_user_timezone(). Deprecated in drupal:8.8.0 and is removed from drupal:9.0.0. Use&#10;date_default_timezone_get() instead." severity="warning"/></file><file name="modules/contrib/clickandpledge_connect/src/Form/CnPAccountForm.php"><error line="233" message="Call to deprecated function drupal_get_user_timezone(). Deprecated in drupal:8.8.0 and is removed from drupal:9.0.0. Use&#10;date_default_timezone_get() instead." severity="warning"/></file><file name="modules/contrib/clickandpledge_connect/src/Form/CnPpledgeTVChannels.php"><error line="226" message="Call to deprecated function drupal_get_user_timezone(). Deprecated in drupal:8.8.0 and is removed from drupal:9.0.0. Use&#10;date_default_timezone_get() instead." severity="warning"/></file><file name="modules/contrib/clickandpledge_connect/src/Form/EditChannels.php"><error line="113" message="Call to deprecated function drupal_get_user_timezone(). Deprecated in drupal:8.8.0 and is removed from drupal:9.0.0. Use&#10;date_default_timezone_get() instead." severity="warning"/><error line="185" message="Call to deprecated function drupal_get_user_timezone(). Deprecated in drupal:8.8.0 and is removed from drupal:9.0.0. Use&#10;date_default_timezone_get() instead." severity="warning"/></file><file name="modules/contrib/clickandpledge_connect/src/Form/EditForms.php"><error line="107" message="Call to deprecated function drupal_get_user_timezone(). Deprecated in drupal:8.8.0 and is removed from drupal:9.0.0. Use&#10;date_default_timezone_get() instead." severity="warning"/><error line="228" message="Call to deprecated function drupal_get_user_timezone(). Deprecated in drupal:8.8.0 and is removed from drupal:9.0.0. Use&#10;date_default_timezone_get() instead." severity="warning"/></file></checkstyle>

