<?xml version="1.0"?>
<checkstyle><file name="modules/contrib/taxonomy_path/src/Plugin/Field/FieldFormatter/TaxonomyPathFormatter.php"><error line="119" message="Call to deprecated method urlInfo() of class Drupal\Core\Entity\EntityInterface. Deprecated in drupal:8.0.0 and is removed from drupal:9.0.0.&#10;Use \Drupal\Core\Entity\EntityInterface::toUrl() instead." severity="error"/><error line="186" message="Call to deprecated method strtoupper() of class Drupal\Component\Utility\Unicode. Deprecated in drupal:8.6.0 and is removed from drupal:9.0.0. Use&#10;mb_strtoupper() instead." severity="error"/><error line="188" message="Call to deprecated method strtolower() of class Drupal\Component\Utility\Unicode. Deprecated in drupal:8.6.0 and is removed from drupal:9.0.0. Use&#10;mb_strtolower() instead." severity="error"/></file><file name="modules/contrib/taxonomy_path/taxonomy_path.info.yml"><error line="0" message="Add &lt;code&gt;core_version_requirement: ^8 || ^9&lt;/code&gt; to taxonomy_path.info.yml to designate that the module is compatible with Drupal 9. See https://www.drupal.org/node/3070687." severity="error"/></file><file name="modules/contrib/taxonomy_path/composer.json"><error line="0" message="A drupal/core requirement is not present in composer.json. Having a composer.json is not a requirement for Drupal 9 compatibility but if there is one, it should include a drupal/core requirement." severity="error"/></file></checkstyle>

