<?xml version="1.0"?>
<checkstyle><file name="modules/contrib/views_conditional/src/Plugin/views/field/ViewsConditionalField.php"><error line="130" message="Call to deprecated function format_date(). Deprecated in drupal:8.0.0 and is removed from drupal:9.0.0.&#10;Use \Drupal::service('date.formatter')-&gt;format()." severity="error"/><error line="210" message="Call to deprecated function format_date(). Deprecated in drupal:8.0.0 and is removed from drupal:9.0.0.&#10;Use \Drupal::service('date.formatter')-&gt;format()." severity="error"/><error line="213" message="Call to deprecated function format_date(). Deprecated in drupal:8.0.0 and is removed from drupal:9.0.0.&#10;Use \Drupal::service('date.formatter')-&gt;format()." severity="error"/><error line="216" message="Call to deprecated function format_date(). Deprecated in drupal:8.0.0 and is removed from drupal:9.0.0.&#10;Use \Drupal::service('date.formatter')-&gt;format()." severity="error"/></file><file name="modules/contrib/views_conditional/views_conditional.info.yml"><error line="0" message="Add &lt;code&gt;core_version_requirement: ^8 || ^9&lt;/code&gt; to views_conditional.info.yml to designate that the module is compatible with Drupal 9. See https://www.drupal.org/node/3070687." severity="error"/></file></checkstyle>

